meow/__init__.py
shopify_mcp_bridge-0.1.5.dist-info/METADATA
shopify_mcp_bridge-0.1.5.dist-info/WHEEL
shopify_mcp_bridge-0.1.5.dist-info/top_level.txt
shopify_mcp_bridge-0.1.5.dist-info/RECORD
