Metadata-Version: 2.4
Name: shopify-mcp-bridge
Version: 0.1.5
Summary: Determines if a string is a meow
Requires-Python: >=3.13
Requires-Dist: pytest>=8.3.4
